{
  "1": {
    "significado": "Soledad e independencia. Energía del individualismo, liderazgo y comienzos."
  },
  "2": {
    "significado": "Emociones y sentimientos. Sensibilidad, compasión y necesidad de apoyo."
  },
  "3": {
    "significado": "Comunicación y creatividad. Determinación, sociabilidad y adaptación."
  },
  "4": {
    "significado": "Desarrollo y construcción. Pragmatismo, practicidad, estabilidad, lógica y orden."
  },
  "5": {
    "significado": "Integración del hombre. Símbolo de vida, energía vital, agilidad y libertad."
  },
  "6": {
    "significado": "Equilibrio entre el universo y el hombre. Hogar, belleza y amor."
  },
  "7": {
    "significado": "Número sagrado. Conocimiento, fe, espiritualidad, energía mental y ciencia."
  },
  "8": {
    "significado": "Dominio de cuerpo y mente. Símbolo del infinito, justicia, renacimiento y futuro."
  },
  "9": {
    "significado": "Amor universal. Idealismo, altruismo, nobleza y artes."
  },
  "10": {
    "significado": "Orden divino y plenitud. Representa un nuevo comienzo en un nivel superior."
  }
{
  "1": {
    "significado_negativo": "Egoísmo, soledad, dominación, dependencia."
  },
  "2": {
    "significado_negativo": "Inseguridad, dependencia, pasividad, sumisión."
  },
  "3": {
    "significado_negativo": "Superficialidad, dispersión, exageración, falta de dirección."
  },
  "4": {
    "significado_negativo": "Rigidez, aburrimiento, dogmatismo, obstinación."
  },
  "5": {
    "significado_negativo": "Impaciencia, inconstancia, impulsividad, irresponsabilidad."
  },
  "6": {
    "significado_negativo": "Ansiedad, celos, servilismo, sacrificio excesivo."
  },
  "7": {
    "significado_negativo": "Aislamiento, melancolía, reclusión, pereza."
  },
  "8": {
    "significado_negativo": "Materialismo, codicia, abuso de poder, agresividad."
  },
  "9": {
    "significado_negativo": "Egocentrismo, falta de compromiso, pérdida, desilusión."
  },
  "10": {
    "significado_negativo": "Tirania, exceso de control, inflexibilidad, arrogancia."
}
